keymanager_hjy/__init__.py
keymanager_hjy/_master.py
keymanager_hjy/async_auth_service.py
keymanager_hjy/async_db_init.py
keymanager_hjy/async_integrations.py
keymanager_hjy/async_keys_service.py
keymanager_hjy/async_master.py
keymanager_hjy/async_redis_limiter.py
keymanager_hjy/async_settings_service.py
keymanager_hjy/auth_cache.py
keymanager_hjy/auth_service.py
keymanager_hjy/cli.py
keymanager_hjy/config_provider.py
keymanager_hjy/db_init.py
keymanager_hjy/exceptions.py
keymanager_hjy/integrations.py
keymanager_hjy/keys_service.py
keymanager_hjy/redis_limiter.py
keymanager_hjy/schema.py
keymanager_hjy/settings_service.py
keymanager_hjy/sync_wrapper.py
keymanager_hjy/tags_service.py
keymanager_hjy/utils.py
keymanager_hjy-0.3.0.dist-info/licenses/LICENSE
keymanager_hjy-0.3.0.dist-info/METADATA
keymanager_hjy-0.3.0.dist-info/WHEEL
keymanager_hjy-0.3.0.dist-info/entry_points.txt
keymanager_hjy-0.3.0.dist-info/top_level.txt
keymanager_hjy-0.3.0.dist-info/RECORD
