Metadata-Version: 2.4
Name: keymanager-hjy
Version: 0.3.0
Summary: Zero-config, professional-grade API security manager. Elegant authentication, rate limiting, and audit logging for modern Python APIs.
Author-email: hjy <hjy@example.com>
Maintainer-email: hjy <hjy@example.com>
License: MIT
Project-URL: Homepage, https://github.com/hjy/keymanager_hjy
Project-URL: Repository, https://github.com/hjy/keymanager_hjy.git
Project-URL: Documentation, https://github.com/hjy/keymanager_hjy#readme
Project-URL: Issues, https://github.com/hjy/keymanager_hjy/issues
Project-URL: Changelog, https://github.com/hjy/keymanager_hjy/releases
Keywords: security,authentication,api,rate-limiting,audit-logging
Classifier: Development Status :: 4 - Beta
Classifier: Intended Audience :: Developers
Classifier: License :: OSI Approved :: MIT License
Classifier: Operating System :: OS Independent
Classifier: Programming Language :: Python :: 3
Classifier: Programming Language :: Python :: 3.8
Classifier: Programming Language :: Python :: 3.9
Classifier: Programming Language :: Python :: 3.10
Classifier: Programming Language :: Python :: 3.11
Classifier: Programming Language :: Python :: 3.12
Classifier: Topic :: Security
Classifier: Topic :: Software Development :: Libraries :: Python Modules
Requires-Python: >=3.8
License-File: LICENSE
Requires-Dist: redis>=4.5.0
Requires-Dist: mysql-connector-python
Requires-Dist: sqlalchemy[asyncio]>=2.0.0
Requires-Dist: aiomysql>=0.2.0
Provides-Extra: fastapi
Requires-Dist: fastapi>=0.100.0; extra == "fastapi"
Provides-Extra: flask
Requires-Dist: flask>=2.3.0; extra == "flask"
Provides-Extra: cli
Requires-Dist: click>=8.0.0; extra == "cli"
Requires-Dist: rich>=13.0.0; extra == "cli"
Provides-Extra: docs
Requires-Dist: mkdocs>=1.5.0; extra == "docs"
Requires-Dist: mkdocs-material>=9.0.0; extra == "docs"
Provides-Extra: test
Requires-Dist: pytest>=7.0.0; extra == "test"
Requires-Dist: pytest-asyncio>=0.21.0; extra == "test"
Requires-Dist: httpx>=0.24.0; extra == "test"
Provides-Extra: dev
Requires-Dist: black>=23.0.0; extra == "dev"
Requires-Dist: isort>=5.12.0; extra == "dev"
Requires-Dist: flake8>=6.0.0; extra == "dev"
Provides-Extra: all
Requires-Dist: fastapi>=0.100.0; extra == "all"
Requires-Dist: flask>=2.3.0; extra == "all"
Requires-Dist: click>=8.0.0; extra == "all"
Requires-Dist: rich>=13.0.0; extra == "all"
Requires-Dist: mkdocs>=1.5.0; extra == "all"
Requires-Dist: mkdocs-material>=9.0.0; extra == "all"
Requires-Dist: pytest>=7.0.0; extra == "all"
Requires-Dist: pytest-asyncio>=0.21.0; extra == "all"
Requires-Dist: httpx>=0.24.0; extra == "all"
Requires-Dist: black>=23.0.0; extra == "all"
Requires-Dist: isort>=5.12.0; extra == "all"
Requires-Dist: flake8>=6.0.0; extra == "all"
Dynamic: license-file
